{".class": "MypyFile", "_fullname": "hyperdiv.components.nav", "future_import_flags": [], "is_partial_stub_package": false, "is_stub": false, "names": {".class": "SymbolTable", "__annotations__": {".class": "SymbolTableNode", "kind": "Gdef", "node": {".class": "Var", "flags": ["is_ready"], "fullname": "hyperdiv.components.nav.__annotations__", "name": "__annotations__", "type": {".class": "Instance", "args": ["builtins.str", {".class": "AnyType", "missing_import_name": null, "source_any": null, "type_of_any": 6}], "type_ref": "builtins.dict"}}}, "__doc__": {".class": "SymbolTableNode", "kind": "Gdef", "node": {".class": "Var", "flags": ["is_ready"], "fullname": "hyperdiv.components.nav.__doc__", "name": "__doc__", "type": "builtins.str"}}, "__file__": {".class": "SymbolTableNode", "kind": "Gdef", "node": {".class": "Var", "flags": ["is_ready"], "fullname": "hyperdiv.components.nav.__file__", "name": "__file__", "type": "builtins.str"}}, "__name__": {".class": "SymbolTableNode", "kind": "Gdef", "node": {".class": "Var", "flags": ["is_ready"], "fullname": "hyperdiv.components.nav.__name__", "name": "__name__", "type": "builtins.str"}}, "__package__": {".class": "SymbolTableNode", "kind": "Gdef", "node": {".class": "Var", "flags": ["is_ready"], "fullname": "hyperdiv.components.nav.__package__", "name": "__package__", "type": "builtins.str"}}, "box": {".class": "SymbolTableNode", "cross_ref": "hyperdiv.components.box.box", "kind": "Gdef"}, "nav": {".class": "SymbolTableNode", "kind": "Gdef", "node": {".class": "TypeInfo", "_promote": null, "abstract_attributes": [], "bases": ["hyperdiv.components.box.box"], "declared_metaclass": null, "defn": {".class": "ClassDef", "fullname": "hyperdiv.components.nav.nav", "name": "nav", "type_vars": []}, "deletable_attributes": [], "flags": [], "fullname": "hyperdiv.components.nav.nav", "has_param_spec_type": false, "metaclass_type": null, "metadata": {}, "module_name": "hyperdiv.components.nav", "mro": ["hyperdiv.components.nav.nav", "hyperdiv.components.box.box", "hyperdiv.component_base.Component", "hyperdiv.collector.Collector", "hyperdiv.component_mixins.Boxy", "hyperdiv.component_mixins.Styled", "hyperdiv.component_mixins.Slottable", "builtins.object"], "names": {".class": "SymbolTable", "_tag": {".class": "SymbolTableNode", "kind": "Mdef", "node": {".class": "Var", "flags": ["is_initialized_in_class", "is_ready", "has_explicit_value"], "fullname": "hyperdiv.components.nav.nav._tag", "name": "_tag", "type": "builtins.str"}}}, "slots": null, "tuple_type": null, "type_vars": [], "typeddict_type": null}}}, "path": "/Users/marius/Code/hyperdiv-shoelace/hyperdiv/components/nav.py"}