{"data_mtime": 1693861283, "dep_lines": [1, 2, 3, 1, 1], "dep_prios": [5, 5, 5, 5, 30], "dependencies": ["_typeshed", "types", "typing", "builtins", "abc"], "hash": "635f6f91cb2c853db51fd7c8bb22aca3f8ecb83174836c9f074c19b3704e3fed", "id": "runpy", "ignore_all": true, "interface_hash": "22015573248333d91e5fe80404aef6e1b181bd394b569c31049de4ad82b0ab78", "mtime": 1689795051, "options": {"allow_redefinition": false, "allow_untyped_globals": false, "always_false": [], "always_true": [], "bazel": false, "check_untyped_defs": false, "disallow_any_decorated": false, "disallow_any_explicit": false, "disallow_any_expr": false, "disallow_any_generics": false, "disallow_any_unimported": false, "disallow_incomplete_defs": false, "disallow_subclassing_any": false, "disallow_untyped_calls": false, "disallow_untyped_decorators": false, "disallow_untyped_defs": false, "follow_imports": "normal", "follow_imports_for_stubs": false, "ignore_errors": false, "ignore_missing_imports": true, "implicit_reexport": true, "local_partial_types": false, "mypyc": false, "no_implicit_optional": false, "platform": "darwin", "plugins": [], "show_none_errors": true, "strict_concatenate": false, "strict_equality": false, "strict_optional": true, "strict_optional_whitelist": null, "warn_no_return": true, "warn_return_any": false, "warn_unreachable": false, "warn_unused_ignores": false}, "path": "/Users/marius/Code/hyperdiv-shoelace/.venv/lib/python3.10/site-packages/mypy/typeshed/stdlib/runpy.pyi", "plugin_data": null, "size": 774, "suppressed": [], "version_id": "0.961"}