{".class": "MypyFile", "_fullname": "hyperdiv.state", "future_import_flags": [], "is_partial_stub_package": false, "is_stub": false, "names": {".class": "SymbolTable", "Frame": {".class": "SymbolTableNode", "cross_ref": "hyperdiv.frame.Frame", "kind": "Gdef"}, "FramePhase": {".class": "SymbolTableNode", "cross_ref": "hyperdiv.frame.FramePhase", "kind": "Gdef"}, "State": {".class": "SymbolTableNode", "kind": "Gdef", "node": {".class": "TypeInfo", "_promote": null, "abstract_attributes": [], "bases": ["builtins.object"], "declared_metaclass": null, "defn": {".class": "ClassDef", "fullname": "hyperdiv.state.State", "name": "State", "type_vars": []}, "deletable_attributes": [], "flags": [], "fullname": "hyperdiv.state.State", "has_param_spec_type": false, "metaclass_type": null, "metadata": {}, "module_name": "hyperdiv.state", "mro": ["hyperdiv.state.State", "builtins.object"], "names": {".class": "SymbolTable", "__init__": {".class": "SymbolTableNode", "kind": "Mdef", "node": {".class": "FuncDef", "arg_kinds": [0], "arg_names": ["self"], "flags": [], "fullname": "hyperdiv.state.State.__init__", "name": "__init__", "type": null}}, "_register_mutation": {".class": "SymbolTableNode", "kind": "Mdef", "node": {".class": "FuncDef", "arg_kinds": [0, 0, 0], "arg_names": ["self", "frame", "prop"], "flags": [], "fullname": "hyperdiv.state.State._register_mutation", "name": "_register_mutation", "type": null}}, "get": {".class": "SymbolTableNode", "kind": "Mdef", "node": {".class": "Decorator", "func": {".class": "FuncDef", "arg_kinds": [0, 0, 0], "arg_names": ["self", "key", "prop_name"], "flags": ["is_decorated"], "fullname": "hyperdiv.state.State.get", "name": "get", "type": null}, "is_overload": false, "var": {".class": "Var", "flags": ["is_initialized_in_class", "is_ready"], "fullname": null, "name": "get", "type": {".class": "AnyType", "missing_import_name": null, "source_any": null, "type_of_any": 1}}}}, "get_props": {".class": "SymbolTableNode", "kind": "Mdef", "node": {".class": "Decorator", "func": {".class": "FuncDef", "arg_kinds": [0, 0], "arg_names": ["self", "key"], "flags": ["is_decorated"], "fullname": "hyperdiv.state.State.get_props", "name": "get_props", "type": null}, "is_overload": false, "var": {".class": "Var", "flags": ["is_initialized_in_class", "is_ready"], "fullname": null, "name": "get_props", "type": {".class": "AnyType", "missing_import_name": null, "source_any": null, "type_of_any": 1}}}}, "has_prop": {".class": "SymbolTableNode", "kind": "Mdef", "node": {".class": "Decorator", "func": {".class": "FuncDef", "arg_kinds": [0, 0, 0], "arg_names": ["self", "key", "prop_name"], "flags": ["is_decorated"], "fullname": "hyperdiv.state.State.has_prop", "name": "has_prop", "type": null}, "is_overload": false, "var": {".class": "Var", "flags": ["is_initialized_in_class", "is_ready"], "fullname": null, "name": "has_prop", "type": {".class": "AnyType", "missing_import_name": null, "source_any": null, "type_of_any": 1}}}}, "init_props": {".class": "SymbolTableNode", "kind": "Mdef", "node": {".class": "Decorator", "func": {".class": "FuncDef", "arg_kinds": [0, 0, 0], "arg_names": ["self", "key", "props_with_values"], "flags": ["is_decorated"], "fullname": "hyperdiv.state.State.init_props", "name": "init_props", "type": null}, "is_overload": false, "var": {".class": "Var", "flags": ["is_initialized_in_class", "is_ready"], "fullname": null, "name": "init_props", "type": {".class": "AnyType", "missing_import_name": null, "source_any": null, "type_of_any": 1}}}}, "reset": {".class": "SymbolTableNode", "kind": "Mdef", "node": {".class": "Decorator", "func": {".class": "FuncDef", "arg_kinds": [0, 0, 0], "arg_names": ["self", "key", "prop_name"], "flags": ["is_decorated"], "fullname": "hyperdiv.state.State.reset", "name": "reset", "type": null}, "is_overload": false, "var": {".class": "Var", "flags": ["is_initialized_in_class", "is_ready"], "fullname": null, "name": "reset", "type": {".class": "AnyType", "missing_import_name": null, "source_any": null, "type_of_any": 1}}}}, "state": {".class": "SymbolTableNode", "implicit": true, "kind": "Mdef", "node": {".class": "Var", "flags": [], "fullname": "hyperdiv.state.State.state", "name": "state", "type": {".class": "AnyType", "missing_import_name": null, "source_any": null, "type_of_any": 1}}}, "state_lock": {".class": "SymbolTableNode", "implicit": true, "kind": "Mdef", "node": {".class": "Var", "flags": [], "fullname": "hyperdiv.state.State.state_lock", "name": "state_lock", "type": {".class": "AnyType", "missing_import_name": null, "source_any": null, "type_of_any": 1}}}, "update": {".class": "SymbolTableNode", "kind": "Mdef", "node": {".class": "Decorator", "func": {".class": "FuncDef", "arg_kinds": [0, 0, 0, 0], "arg_names": ["self", "key", "prop_name", "value"], "flags": ["is_decorated"], "fullname": "hyperdiv.state.State.update", "name": "update", "type": null}, "is_overload": false, "var": {".class": "Var", "flags": ["is_initialized_in_class", "is_ready"], "fullname": null, "name": "update", "type": {".class": "AnyType", "missing_import_name": null, "source_any": null, "type_of_any": 1}}}}}, "slots": null, "tuple_type": null, "type_vars": [], "typeddict_type": null}}, "StoredProp": {".class": "SymbolTableNode", "cross_ref": "hyperdiv.prop.StoredProp", "kind": "Gdef"}, "__annotations__": {".class": "SymbolTableNode", "kind": "Gdef", "node": {".class": "Var", "flags": ["is_ready"], "fullname": "hyperdiv.state.__annotations__", "name": "__annotations__", "type": {".class": "Instance", "args": ["builtins.str", {".class": "AnyType", "missing_import_name": null, "source_any": null, "type_of_any": 6}], "type_ref": "builtins.dict"}}}, "__doc__": {".class": "SymbolTableNode", "kind": "Gdef", "node": {".class": "Var", "flags": ["is_ready"], "fullname": "hyperdiv.state.__doc__", "name": "__doc__", "type": "builtins.str"}}, "__file__": {".class": "SymbolTableNode", "kind": "Gdef", "node": {".class": "Var", "flags": ["is_ready"], "fullname": "hyperdiv.state.__file__", "name": "__file__", "type": "builtins.str"}}, "__name__": {".class": "SymbolTableNode", "kind": "Gdef", "node": {".class": "Var", "flags": ["is_ready"], "fullname": "hyperdiv.state.__name__", "name": "__name__", "type": "builtins.str"}}, "__package__": {".class": "SymbolTableNode", "kind": "Gdef", "node": {".class": "Var", "flags": ["is_ready"], "fullname": "hyperdiv.state.__package__", "name": "__package__", "type": "builtins.str"}}, "in_frame": {".class": "SymbolTableNode", "cross_ref": "hyperdiv.frame.in_frame", "kind": "Gdef"}, "threading": {".class": "SymbolTableNode", "cross_ref": "threading", "kind": "Gdef"}}, "path": "/Users/marius/Code/hyperdiv-shoelace/hyperdiv/state.py"}