{"id": "hashlib", "path": "/Users/marius/Code/hyperdiv-shoelace/.venv/lib/python3.10/site-packages/mypy/typeshed/stdlib/hashlib.pyi", "mtime": 1689795051, "size": 5546, "hash": "464836ff95a6fba05f8f35dc28de46dbdec54b3b3c30286b19fa8f6dccaabccc", "data_mtime": 1674517868, "dependencies": ["sys", "_typeshed", "collections.abc", "typing", "typing_extensions", "builtins", "abc", "array", "ctypes", "mmap", "pickle"], "suppressed": [], "options": {"warn_unreachable": false, "ignore_missing_imports": true, "warn_return_any": false, "allow_redefinition": false, "bazel": false, "strict_equality": false, "disallow_any_explicit": false, "disallow_untyped_calls": false, "disallow_any_expr": false, "disallow_untyped_defs": false, "warn_no_return": true, "always_false": [], "platform": "darwin", "local_partial_types": false, "follow_imports": "normal", "follow_imports_for_stubs": false, "disallow_any_generics": false, "disallow_untyped_decorators": false, "disallow_subclassing_any": false, "mypyc": false, "strict_optional_whitelist": null, "strict_optional": true, "check_untyped_defs": false, "implicit_reexport": true, "disallow_incomplete_defs": false, "strict_concatenate": false, "disallow_any_unimported": false, "warn_unused_ignores": false, "plugins": [], "show_none_errors": true, "always_true": [], "ignore_errors": false, "no_implicit_optional": false, "allow_untyped_globals": false, "disallow_any_decorated": false}, "dep_prios": [10, 5, 5, 5, 5, 5, 30, 30, 30, 30, 30], "dep_lines": [1, 2, 3, 4, 5, 1, 1, 1, 1, 1, 1], "interface_hash": "23b434fc07c09f712360f2335e2c875c1d5e659e202c63eae66abbf5e1f20e13", "version_id": "0.961", "ignore_all": true, "plugin_data": null}