{"id": "doctest", "path": "/Users/marius/Code/hyperdiv-shoelace/.venv/lib/python3.11/site-packages/mypy/typeshed/stdlib/doctest.pyi", "mtime": 1697484951, "size": 7634, "hash": "a8019dfe87992da258d65debcb40654f2afdfe96e912f11a79df02118e0d2cc5", "data_mtime": 1695327057, "dependencies": ["types", "unittest", "_typeshed", "collections.abc", "typing", "typing_extensions", "builtins", "abc"], "suppressed": [], "options": {"strict_optional": true, "warn_unreachable": false, "always_false": [], "disallow_incomplete_defs": false, "disallow_subclassing_any": false, "follow_imports_for_stubs": false, "disallow_any_decorated": false, "plugins": [], "implicit_reexport": true, "no_implicit_optional": false, "warn_return_any": false, "allow_untyped_globals": false, "follow_imports": "normal", "ignore_errors": false, "show_none_errors": true, "disallow_any_unimported": false, "warn_unused_ignores": false, "warn_no_return": true, "allow_redefinition": false, "disallow_any_expr": false, "local_partial_types": false, "check_untyped_defs": false, "always_true": [], "disallow_any_generics": false, "strict_concatenate": false, "strict_equality": false, "disallow_untyped_decorators": false, "mypyc": false, "ignore_missing_imports": true, "disallow_untyped_defs": false, "strict_optional_whitelist": null, "disallow_untyped_calls": false, "platform": "darwin", "bazel": false, "disallow_any_explicit": false}, "dep_prios": [10, 10, 5, 5, 5, 5, 5, 30], "dep_lines": [1, 2, 3, 4, 5, 6, 1, 1], "interface_hash": "0e8dbcab466687c4ad056d1d4979fb5705f35a7923aa658bc8a4023d485483ac", "version_id": "0.961", "ignore_all": true, "plugin_data": null}