{"id": "asyncio", "path": "/Users/marius/Code/hyperdiv-shoelace/.venv/lib/python3.11/site-packages/mypy/typeshed/stdlib/asyncio/__init__.pyi", "mtime": 1697484951, "size": 694, "hash": "2f947ccf4a3be6541bfd42bb796855b6b110bedfb0c197a8f6c0440dc5f1f2e3", "data_mtime": 1696019227, "dependencies": ["sys", "asyncio.base_events", "asyncio.coroutines", "asyncio.events", "asyncio.futures", "asyncio.locks", "asyncio.protocols", "asyncio.queues", "asyncio.streams", "asyncio.subprocess", "asyncio.tasks", "asyncio.transports", "asyncio.runners", "asyncio.exceptions", "asyncio.threads", "asyncio.taskgroups", "asyncio.unix_events", "builtins", "_typeshed", "abc", "typing"], "suppressed": [], "options": {"disallow_subclassing_any": false, "ignore_missing_imports": true, "allow_untyped_globals": false, "strict_concatenate": false, "follow_imports_for_stubs": false, "ignore_errors": false, "always_false": [], "local_partial_types": false, "warn_unused_ignores": false, "disallow_any_generics": false, "disallow_untyped_defs": false, "disallow_incomplete_defs": false, "bazel": false, "disallow_any_expr": false, "check_untyped_defs": false, "disallow_any_unimported": false, "warn_return_any": false, "disallow_untyped_decorators": false, "implicit_reexport": true, "always_true": [], "warn_no_return": true, "strict_optional": true, "follow_imports": "normal", "warn_unreachable": false, "allow_redefinition": false, "disallow_any_explicit": false, "disallow_any_decorated": false, "strict_optional_whitelist": null, "platform": "darwin", "mypyc": false, "plugins": [], "disallow_untyped_calls": false, "no_implicit_optional": false, "strict_equality": false, "show_none_errors": true}, "dep_prios": [10, 5, 5, 5, 5, 5, 5, 5, 5, 5, 5, 5, 5, 5, 5, 5, 5, 5, 30, 30, 30], "dep_lines": [1, 4, 5, 6, 7, 8, 9, 10, 11, 12, 13, 14, 17, 20, 23, 26, 31, 1, 1, 1, 1], "interface_hash": "2e1288b9ff3dda3f8f743e7d9c21f901ea3f43598ec36ec5928f06b832c5e34f", "version_id": "0.961", "ignore_all": true, "plugin_data": null}